{
  "parent": "bigstone_sandbox:item/tri_right",
  "display": {
    "thirdperson_righthand": {
      "translation": [
        -9.9,
        -0.96,
        4.25
      ],
      "scale": [
        0.55,
        0.55,
        0.55
      ]
    },
    "thirdperson_lefthand": {
      "translation": [
        -9.9,
        -0.96,
        4.25
      ],
      "scale": [
        0.55,
        0.55,
        0.55
      ]
    },
    "ground": {
      "translation": [
        -4.75,
        1.63,
        -0.5
      ],
      "rotation": [
        0,
        90,
        0
      ],
      "scale": [
        0.5,
        0.5,
        0.5
      ]
    },
    "head": {
      "translation": [
        -15.12,
        -1.46,
        0
      ],
      "scale": [
        0.84,
        0.84,
        0.84
      ]
    },
    "fixed": {
      "translation": [
        -18,
        -1.74,
        -8.1
      ],
      "rotation": [
        0,
        -180,
        0
      ],
      "scale": [
        1,
        1,
        1
      ]
    },
    "on_shelf": {
      "translation": [
        -18,
        -1.74,
        5.75
      ],
      "scale": [
        1,
        1,
        1
      ]
    }
  },
  "gui_light": "front"
}