{
  "parent": "bigstone_sandbox:item/display_base",
  "elements": [
    {
      "from": [
        9.99,
        -7.51,
        8
      ],
      "to": [
        11.01,
        -6.49,
        8
      ],
      "faces": {
        "north": {
          "uv": [
            0,
            0,
            16,
            16
          ],
          "texture": "#1",
          "tintindex": 0
        },
        "south": {
          "uv": [
            16,
            0,
            0,
            16
          ],
          "texture": "#1",
          "tintindex": 0
        }
      }
    }
  ]
}