{
  "parent": "bigstone_sandbox:item/v",
  "elements": [
    {
      "from": [
        7,
        15,
        4
      ],
      "to": [
        8,
        16,
        5
      ],
      "faces": {
        "north": {
          "uv": [
            8,
            0,
            9,
            1
          ],
          "texture": "#1",
          "tintindex": 0
        },
        "east": {
          "uv": [
            11,
            0,
            12,
            1
          ],
          "texture": "#1",
          "tintindex": 0
        },
        "up": {
          "uv": [
            7,
            4,
            8,
            5
          ],
          "texture": "#1",
          "tintindex": 0
        }
      }
    }
  ]
}